CSF_3DFin/CSF_3DFin_ext.pyi
CSF_3DFin/__init__.py
CSF_3DFin/CSF_3DFin_ext.cpython-312-darwin.so
csf_3dfin-2.0.1.dist-info/RECORD
csf_3dfin-2.0.1.dist-info/WHEEL
csf_3dfin-2.0.1.dist-info/METADATA
csf_3dfin-2.0.1.dist-info/licenses/LICENSE.txt
