Metadata-Version: 2.1
Name: CSF_3DFin
Version: 2.0.1
Summary: CSF: Ground Filtering based on Cloth Simulation
Keywords: LiDAR,DTM,DSM,Classification
Author-Email: Jianbo Qi <jianboqi@126.com>
Maintainer-Email: Romain Janvier <romain.janvier@hotmail.fr>
License:                                  Apache License
Project-URL: Repository, https://github.com/3DFin/CSF-3DFIN
Requires-Python: <3.14,>=3.10
Requires-Dist: laspy>=2.5.4
Requires-Dist: numpy>1.23
